<?xml version="1.0"?>
<?mso-application progid="Excel.Sheet"?>
<Workbook xmlns="urn:schemas-microsoft-com:office:spreadsheet"
 xmlns:o="urn:schemas-microsoft-com:office:office"
 xmlns:x="urn:schemas-microsoft-com:office:excel"
 xmlns:ss="urn:schemas-microsoft-com:office:spreadsheet"
 xmlns:html="http://www.w3.org/TR/REC-html40">
 <DocumentProperties xmlns="urn:schemas-microsoft-com:office:office">
  <Created>2006-09-16T00:00:00Z</Created>
  <LastSaved>2015-07-06T07:38:48Z</LastSaved>
  <Version>14.00</Version>
 </DocumentProperties>
 <OfficeDocumentSettings xmlns="urn:schemas-microsoft-com:office:office">
  <AllowPNG/>
  <RemovePersonalInformation/>
 </OfficeDocumentSettings>
 <ExcelWorkbook xmlns="urn:schemas-microsoft-com:office:excel">
  <WindowHeight>6945</WindowHeight>
  <WindowWidth>14805</WindowWidth>
  <WindowTopX>240</WindowTopX>
  <WindowTopY>405</WindowTopY>
  <TabRatio>932</TabRatio>
  <RefModeR1C1/>
  <ProtectStructure>False</ProtectStructure>
  <ProtectWindows>False</ProtectWindows>
 </ExcelWorkbook>
 <Styles>
  <Style ss:ID="Default" ss:Name="Normal">
   <Alignment ss:Vertical="Bottom"/>
   <Borders/>
   <Font ss:FontName="Calibri" x:Family="Swiss" ss:Size="11" ss:Color="#000000"/>
   <Interior/>
   <NumberFormat/>
   <Protection/>
  </Style>
  <Style ss:ID="s62">
   <Font ss:FontName="Calibri" x:Family="Swiss" ss:Size="11"/>
  </Style>
  <Style ss:ID="s63">
   <Font ss:FontName="Calibri" x:Family="Swiss" ss:Size="11"/>
   <NumberFormat ss:Format="Fixed"/>
  </Style>
  <Style ss:ID="s64">
   <Font ss:FontName="Times New Roman" x:CharSet="204" x:Family="Roman"
    ss:Size="16" ss:Bold="1"/>
  </Style>
  <Style ss:ID="s65">
   <Alignment ss:Horizontal="Center" ss:Vertical="Center" ss:WrapText="1"/>
   <Borders>
    <Border ss:Position="Bottom" ss:LineStyle="Continuous" ss:Weight="1"/>
    <Border ss:Position="Left" ss:LineStyle="Continuous" ss:Weight="1"/>
    <Border ss:Position="Right" ss:LineStyle="Continuous" ss:Weight="1"/>
    <Border ss:Position="Top" ss:LineStyle="Continuous" ss:Weight="1"/>
   </Borders>
   <Font ss:FontName="Times New Roman" x:CharSet="204" x:Family="Roman"
    ss:Size="12"/>
  </Style>
  <Style ss:ID="s66">
   <Alignment ss:Horizontal="Center" ss:Vertical="Center" ss:WrapText="1"/>
   <Borders>
    <Border ss:Position="Bottom" ss:LineStyle="Continuous" ss:Weight="1"/>
    <Border ss:Position="Left" ss:LineStyle="Continuous" ss:Weight="1"/>
    <Border ss:Position="Right" ss:LineStyle="Continuous" ss:Weight="1"/>
    <Border ss:Position="Top" ss:LineStyle="Continuous" ss:Weight="1"/>
   </Borders>
   <Font ss:FontName="Times New Roman" x:CharSet="204" x:Family="Roman"
    ss:Size="12"/>
   <Interior ss:Color="#FFFFFF" ss:Pattern="Solid"/>
  </Style>
  <Style ss:ID="s67">
   <Alignment ss:Horizontal="Center" ss:Vertical="Center" ss:WrapText="1"/>
   <Borders/>
   <Font ss:FontName="Times New Roman" x:CharSet="204" x:Family="Roman"
    ss:Size="12"/>
   <Interior ss:Color="#FFFFFF" ss:Pattern="Solid"/>
   <NumberFormat ss:Format="Fixed"/>
  </Style>
  <Style ss:ID="s68">
   <Alignment ss:Horizontal="Center" ss:Vertical="Center" ss:WrapText="1"/>
   <Borders>
    <Border ss:Position="Bottom" ss:LineStyle="Continuous" ss:Weight="1"/>
    <Border ss:Position="Left" ss:LineStyle="Continuous" ss:Weight="1"/>
    <Border ss:Position="Right" ss:LineStyle="Continuous" ss:Weight="1"/>
    <Border ss:Position="Top" ss:LineStyle="Continuous" ss:Weight="1"/>
   </Borders>
   <Font ss:FontName="Times New Roman" x:CharSet="204" x:Family="Roman"
    ss:Size="12"/>
   <Interior/>
  </Style>
  <Style ss:ID="s69">
   <Alignment ss:Horizontal="Center" ss:Vertical="Center"/>
   <Borders>
    <Border ss:Position="Bottom" ss:LineStyle="Continuous" ss:Weight="1"/>
    <Border ss:Position="Left" ss:LineStyle="Continuous" ss:Weight="1"/>
    <Border ss:Position="Right" ss:LineStyle="Continuous" ss:Weight="1"/>
    <Border ss:Position="Top" ss:LineStyle="Continuous" ss:Weight="1"/>
   </Borders>
   <Font ss:FontName="Times New Roman" x:CharSet="204" x:Family="Roman"
    ss:Size="12"/>
   <Interior/>
  </Style>
  <Style ss:ID="s70">
   <Alignment ss:Horizontal="Center" ss:Vertical="Center" ss:WrapText="1"/>
   <Borders/>
   <Font ss:FontName="Times New Roman" x:CharSet="204" x:Family="Roman"
    ss:Size="12"/>
   <Interior/>
   <NumberFormat ss:Format="Fixed"/>
  </Style>
  <Style ss:ID="s71">
   <Font ss:FontName="Calibri" x:Family="Swiss" ss:Size="11"/>
   <NumberFormat ss:Format="Short Date"/>
  </Style>
  <Style ss:ID="s72">
   <Borders>
    <Border ss:Position="Bottom" ss:LineStyle="Continuous" ss:Weight="1"/>
    <Border ss:Position="Left" ss:LineStyle="Continuous" ss:Weight="1"/>
    <Border ss:Position="Right" ss:LineStyle="Continuous" ss:Weight="1"/>
    <Border ss:Position="Top" ss:LineStyle="Continuous" ss:Weight="1"/>
   </Borders>
   <Font ss:FontName="Calibri" x:Family="Swiss" ss:Size="11"/>
  </Style>
  <Style ss:ID="s73">
   <Alignment ss:Vertical="Bottom"/>
   <Borders>
    <Border ss:Position="Bottom" ss:LineStyle="Continuous" ss:Weight="1"/>
    <Border ss:Position="Left" ss:LineStyle="Continuous" ss:Weight="1"/>
    <Border ss:Position="Right" ss:LineStyle="Continuous" ss:Weight="1"/>
    <Border ss:Position="Top" ss:LineStyle="Continuous" ss:Weight="1"/>
   </Borders>
   <Font ss:FontName="Calibri" x:Family="Swiss" ss:Size="11"/>
  </Style>
  <Style ss:ID="s74">
   <Alignment ss:Horizontal="Center" ss:Vertical="Bottom"/>
   <Borders>
    <Border ss:Position="Bottom" ss:LineStyle="Continuous" ss:Weight="1"/>
    <Border ss:Position="Left" ss:LineStyle="Continuous" ss:Weight="1"/>
    <Border ss:Position="Right" ss:LineStyle="Continuous" ss:Weight="1"/>
    <Border ss:Position="Top" ss:LineStyle="Continuous" ss:Weight="1"/>
   </Borders>
   <Font ss:FontName="Calibri" x:Family="Swiss" ss:Size="11"/>
   <NumberFormat ss:Format="Short Date"/>
  </Style>
  <Style ss:ID="s75">
   <Alignment ss:Vertical="Top"/>
   <Borders>
    <Border ss:Position="Bottom" ss:LineStyle="Continuous" ss:Weight="1"/>
    <Border ss:Position="Left" ss:LineStyle="Continuous" ss:Weight="1"/>
    <Border ss:Position="Right" ss:LineStyle="Continuous" ss:Weight="1"/>
    <Border ss:Position="Top" ss:LineStyle="Continuous" ss:Weight="1"/>
   </Borders>
   <Font ss:FontName="Arial Cyr" x:CharSet="204"/>
  </Style>
  <Style ss:ID="s76">
   <Alignment ss:Vertical="Bottom"/>
   <Borders>
    <Border ss:Position="Bottom" ss:LineStyle="Continuous" ss:Weight="1"/>
    <Border ss:Position="Left" ss:LineStyle="Continuous" ss:Weight="1"/>
    <Border ss:Position="Right" ss:LineStyle="Continuous" ss:Weight="1"/>
    <Border ss:Position="Top" ss:LineStyle="Continuous" ss:Weight="1"/>
   </Borders>
   <Font ss:FontName="Arial Cyr" x:CharSet="204"/>
  </Style>
  <Style ss:ID="s77">
   <Alignment ss:Vertical="Center" ss:WrapText="1"/>
   <Borders>
    <Border ss:Position="Bottom" ss:LineStyle="Continuous" ss:Weight="1"/>
    <Border ss:Position="Left" ss:LineStyle="Continuous" ss:Weight="1"/>
    <Border ss:Position="Right" ss:LineStyle="Continuous" ss:Weight="1"/>
    <Border ss:Position="Top" ss:LineStyle="Continuous" ss:Weight="1"/>
   </Borders>
   <Font ss:FontName="Arial" x:CharSet="204" x:Family="Swiss"/>
  </Style>
  <Style ss:ID="s78">
   <Alignment ss:Horizontal="Center" ss:Vertical="Top"/>
   <Borders>
    <Border ss:Position="Bottom" ss:LineStyle="Continuous" ss:Weight="1"/>
    <Border ss:Position="Left" ss:LineStyle="Continuous" ss:Weight="1"/>
    <Border ss:Position="Right" ss:LineStyle="Continuous" ss:Weight="1"/>
    <Border ss:Position="Top" ss:LineStyle="Continuous" ss:Weight="1"/>
   </Borders>
   <Font ss:FontName="Arial Cyr" x:CharSet="204"/>
  </Style>
  <Style ss:ID="s79">
   <Alignment ss:Horizontal="Left" ss:Vertical="Top"/>
   <Borders>
    <Border ss:Position="Bottom" ss:LineStyle="Continuous" ss:Weight="1"/>
    <Border ss:Position="Left" ss:LineStyle="Continuous" ss:Weight="1"/>
    <Border ss:Position="Right" ss:LineStyle="Continuous" ss:Weight="1"/>
    <Border ss:Position="Top" ss:LineStyle="Continuous" ss:Weight="1"/>
   </Borders>
   <Font ss:FontName="Arial Cyr" x:CharSet="204"/>
  </Style>
  <Style ss:ID="s80">
   <Borders>
    <Border ss:Position="Bottom" ss:LineStyle="Continuous" ss:Weight="1"/>
    <Border ss:Position="Left" ss:LineStyle="Continuous" ss:Weight="1"/>
    <Border ss:Position="Right" ss:LineStyle="Continuous" ss:Weight="1"/>
    <Border ss:Position="Top" ss:LineStyle="Continuous" ss:Weight="1"/>
   </Borders>
   <Font ss:FontName="Times New Roman" x:CharSet="204" x:Family="Roman"
    ss:Size="11"/>
   <NumberFormat ss:Format="@"/>
  </Style>
  <Style ss:ID="s81">
   <Borders>
    <Border ss:Position="Bottom" ss:LineStyle="Continuous" ss:Weight="1"/>
    <Border ss:Position="Left" ss:LineStyle="Continuous" ss:Weight="1"/>
    <Border ss:Position="Right" ss:LineStyle="Continuous" ss:Weight="1"/>
    <Border ss:Position="Top" ss:LineStyle="Continuous" ss:Weight="1"/>
   </Borders>
   <Font ss:FontName="Times New Roman" x:CharSet="204" x:Family="Roman"
    ss:Size="11"/>
  </Style>
  <Style ss:ID="s82">
   <Borders>
    <Border ss:Position="Bottom" ss:LineStyle="Continuous" ss:Weight="1"/>
    <Border ss:Position="Left" ss:LineStyle="Continuous" ss:Weight="1"/>
    <Border ss:Position="Right" ss:LineStyle="Continuous" ss:Weight="1"/>
    <Border ss:Position="Top" ss:LineStyle="Continuous" ss:Weight="1"/>
   </Borders>
   <Font ss:FontName="Calibri" x:Family="Swiss" ss:Size="11"/>
   <NumberFormat ss:Format="Short Date"/>
  </Style>
  <Style ss:ID="s83">
   <Borders>
    <Border ss:Position="Bottom" ss:LineStyle="Continuous" ss:Weight="1"/>
    <Border ss:Position="Left" ss:LineStyle="Continuous" ss:Weight="1"/>
    <Border ss:Position="Right" ss:LineStyle="Continuous" ss:Weight="1"/>
    <Border ss:Position="Top" ss:LineStyle="Continuous" ss:Weight="1"/>
   </Borders>
   <Font ss:FontName="Calibri" x:Family="Swiss" ss:Size="11"/>
   <NumberFormat ss:Format="Fixed"/>
  </Style>
 </Styles>
 <Worksheet ss:Name="Шаблон 5 Договоры">
  <Table ss:ExpandedColumnCount="73" ss:ExpandedRowCount="5" x:FullColumns="1"
   x:FullRows="1" ss:StyleID="s62" ss:DefaultRowHeight="15">
   <Column ss:StyleID="s62" ss:AutoFitWidth="0" ss:Width="96.75"/>
   <Column ss:StyleID="s62" ss:AutoFitWidth="0" ss:Width="165.75"/>
   <Column ss:StyleID="s62" ss:AutoFitWidth="0" ss:Width="96.75" ss:Span="9"/>
   <Column ss:Index="13" ss:StyleID="s62" ss:AutoFitWidth="0" ss:Width="105"/>
   <Column ss:StyleID="s62" ss:AutoFitWidth="0" ss:Width="107.25"/>
   <Column ss:Index="23" ss:StyleID="s62" ss:AutoFitWidth="0" ss:Width="105"
    ss:Span="4"/>
   <Column ss:Index="28" ss:StyleID="s62" ss:AutoFitWidth="0" ss:Width="111"/>
   <Column ss:StyleID="s62" ss:AutoFitWidth="0" ss:Width="96.75" ss:Span="10"/>
   <Column ss:Index="40" ss:StyleID="s62" ss:Width="129.75"/>
   <Column ss:StyleID="s62" ss:Width="40.5"/>
   <Column ss:StyleID="s62" ss:Width="47.25"/>
   <Column ss:StyleID="s62" ss:Width="156"/>
   <Column ss:StyleID="s62" ss:Width="96"/>
   <Column ss:StyleID="s62" ss:Width="131.25"/>
   <Column ss:StyleID="s62" ss:Width="94.5"/>
   <Column ss:StyleID="s62" ss:Width="56.25"/>
   <Column ss:StyleID="s62" ss:Width="74.25" ss:Span="1"/>
   <Column ss:Index="50" ss:StyleID="s62" ss:Width="66"/>
   <Column ss:StyleID="s62" ss:Width="74.25"/>
   <Column ss:StyleID="s62" ss:Width="71.25"/>
   <Column ss:StyleID="s62" ss:Width="90.75"/>
   <Column ss:StyleID="s62" ss:Width="65.25"/>
   <Column ss:StyleID="s62" ss:Width="165.75"/>
   <Column ss:StyleID="s62" ss:Width="147"/>
   <Column ss:StyleID="s62" ss:Width="56.25"/>
   <Column ss:StyleID="s62" ss:Width="54.75"/>
   <Column ss:StyleID="s62" ss:Width="93.75"/>
   <Column ss:StyleID="s62" ss:AutoFitWidth="0" ss:Width="96.75"/>
   <Column ss:StyleID="s62" ss:Width="85.5"/>
   <Column ss:StyleID="s62" ss:AutoFitWidth="0" ss:Width="74.25"/>
   <Column ss:StyleID="s62" ss:AutoFitWidth="0" ss:Width="71.25"/>
   <Column ss:StyleID="s62" ss:AutoFitWidth="0" ss:Width="117"/>
   <Column ss:StyleID="s62" ss:AutoFitWidth="0" ss:Width="112.5" ss:Span="1"/>
   <Column ss:Index="67" ss:StyleID="s62" ss:AutoFitWidth="0" ss:Width="111.75"/>
   <Column ss:StyleID="s62" ss:AutoFitWidth="0" ss:Width="96"/>
   <Column ss:StyleID="s62" ss:Width="165.75"/>
   <Column ss:StyleID="s62" ss:Width="125.25"/>
   <Column ss:StyleID="s63" ss:Hidden="1" ss:AutoFitWidth="0" ss:Width="125.25"/>
   <Column ss:StyleID="s62" ss:Hidden="1" ss:AutoFitWidth="0" ss:Width="116.25"/>
   <Row ss:AutoFitHeight="0">
    <Cell ss:Index="13" ss:StyleID="s64"
     ss:Formula="= IF(R[4]C[58]&gt;0,CONCATENATE(&quot;Приложение 5 Шаблон предоставления сведений по договорам &quot;,R5C72),&quot;Приложение 5 Шаблон предоставления сведений по договорам &quot;)"><Data
      ss:Type="Error">#VALUE!</Data></Cell>
   </Row>
   <Row ss:Index="3" ss:AutoFitHeight="0" ss:Height="74.25">
    <Cell ss:StyleID="s65"><Data ss:Type="String">Балансовая единица</Data></Cell>
    <Cell ss:StyleID="s65"><Data ss:Type="String">Внешний номер договора</Data></Cell>
    <Cell ss:StyleID="s65"><Data ss:Type="String">Исторический номер</Data></Cell>
    <Cell ss:StyleID="s65"><Data ss:Type="String">Дата договора</Data></Cell>
    <Cell ss:StyleID="s65"><Data ss:Type="String">Тип корректировки</Data></Cell>
    <Cell ss:StyleID="s65"><Data ss:Type="String">Исторический номер ДС</Data></Cell>
    <Cell ss:StyleID="s65"><Data ss:Type="String">Номер документа корректировки договора</Data></Cell>
    <Cell ss:StyleID="s65"><Data ss:Type="String">Дата документа корректировки договора</Data></Cell>
    <Cell ss:StyleID="s65"><Data ss:Type="String">Номер контрагента в системе-источнике</Data></Cell>
    <Cell ss:StyleID="s65"><Data ss:Type="String">ИНН контрагента</Data></Cell>
    <Cell ss:StyleID="s65"><Data ss:Type="String">КПП контрагента </Data></Cell>
    <Cell ss:StyleID="s65"><Data ss:Type="String">Группа</Data></Cell>
    <Cell ss:StyleID="s65"><Data ss:Type="String">Наименование</Data></Cell>
    <Cell ss:StyleID="s65"><Data ss:Type="String">Получатель платежа</Data></Cell>
    <Cell ss:StyleID="s65"><Data ss:Type="String">Краткое наименование организации</Data></Cell>
    <Cell ss:StyleID="s65"><Data ss:Type="String">Страна</Data></Cell>
    <Cell ss:StyleID="s65"><Data ss:Type="String">Почтовый индекс</Data></Cell>
    <Cell ss:StyleID="s65"><Data ss:Type="String">Регион</Data></Cell>
    <Cell ss:StyleID="s65"><Data ss:Type="String">Район</Data></Cell>
    <Cell ss:StyleID="s65"><Data ss:Type="String">Город</Data></Cell>
    <Cell ss:StyleID="s65"><Data ss:Type="String">Улица</Data></Cell>
    <Cell ss:StyleID="s65"><Data ss:Type="String">Номер дома</Data></Cell>
    <Cell ss:StyleID="s65"><Data ss:Type="String">Расчетный счет контрагента</Data></Cell>
    <Cell ss:StyleID="s65"><Data ss:Type="String">БИК банка контрагента</Data></Cell>
    <Cell ss:StyleID="s65"><Data ss:Type="String">Вид договора</Data></Cell>
    <Cell ss:StyleID="s65"><Data ss:Type="String">Тип договора</Data></Cell>
    <Cell ss:StyleID="s65"><Data ss:Type="String">Инициатор договора</Data></Cell>
    <Cell ss:StyleID="s65"><Data ss:Type="String">Предмет договора</Data></Cell>
    <Cell ss:StyleID="s65"><Data ss:Type="String">БИК собственного банка</Data></Cell>
    <Cell ss:StyleID="s65"><Data ss:Type="String">Собственный счет</Data></Cell>
    <Cell ss:StyleID="s65"><Data ss:Type="String">Код валюты документа</Data></Cell>
    <Cell ss:StyleID="s65"><Data ss:Type="String">Курс валюты</Data></Cell>
    <Cell ss:StyleID="s65"><Data ss:Type="String">Сумма договора с НДС</Data></Cell>
    <Cell ss:StyleID="s65"><Data ss:Type="String">Ставка НДС</Data></Cell>
    <Cell ss:StyleID="s65"><Data ss:Type="String">Сумма без НДС</Data></Cell>
    <Cell ss:StyleID="s65"><Data ss:Type="String">Сумма НДС</Data></Cell>
    <Cell ss:StyleID="s65"><Data ss:Type="String">ПФМ</Data></Cell>
    <Cell ss:StyleID="s65"><Data ss:Type="String">Финпозиция</Data></Cell>
    <Cell ss:StyleID="s65"><Data ss:Type="String">Фонд</Data></Cell>
    <Cell ss:StyleID="s65"><Data ss:Type="String">Номер рамочного договора</Data></Cell>
    <Cell ss:StyleID="s66"><Data ss:Type="String">Срок начала периода</Data></Cell>
    <Cell ss:StyleID="s66"><Data ss:Type="String">Срок окончания периода</Data></Cell>
    <Cell ss:StyleID="s66"><Data ss:Type="String">Состояние ликвидности, тыс. руб. </Data></Cell>
    <Cell ss:StyleID="s66"><Data ss:Type="String">Средневзвешенная ставка  по предоставлению заемных средств</Data></Cell>
    <Cell ss:StyleID="s66"><Data ss:Type="String">Средневзвешенная ставка  по размещению временно свободной ликвидности </Data></Cell>
    <Cell ss:StyleID="s66"><Data ss:Type="String">Примечание</Data></Cell>
    <Cell ss:StyleID="s66"><Data ss:Type="String">Дата окончания периода выборки</Data></Cell>
    <Cell ss:StyleID="s66"><Data ss:Type="String">Фактическая сумма по договору</Data></Cell>
    <Cell ss:StyleID="s66"><Data ss:Type="String">Свободный кредитный лимит</Data></Cell>
    <Cell ss:StyleID="s66"><Data ss:Type="String">Возможность банка одностороннего отказа </Data></Cell>
    <Cell ss:StyleID="s66"><Data ss:Type="String">Сумма транша</Data></Cell>
    <Cell ss:StyleID="s66"><Data ss:Type="String">Срок начала периода использования займа </Data></Cell>
    <Cell ss:StyleID="s66"><Data ss:Type="String">Срок окончания периода использования займа </Data></Cell>
    <Cell ss:StyleID="s66"><Data ss:Type="String">Период использования займа, дней</Data></Cell>
    <Cell ss:StyleID="s66"><Data ss:Type="String">Процентная ставка, % годовых</Data></Cell>
    <Cell ss:StyleID="s66"><Data ss:Type="String">Досрочное погашение (ДА/НЕТ)</Data></Cell>
    <Cell ss:StyleID="s66"><Data ss:Type="String">Дата возврата денежных средств</Data></Cell>
    <Cell ss:StyleID="s66"><Data ss:Type="String">Вид размещения</Data></Cell>
    <Cell ss:StyleID="s66"><Data ss:Type="String">Статус </Data></Cell>
    <Cell ss:StyleID="s65"><Data ss:Type="String">Код валюты платежа</Data></Cell>
    <Cell ss:StyleID="s66"><Data ss:Type="String">Дата начала договора</Data></Cell>
    <Cell ss:StyleID="s66"><Data ss:Type="String">Дата окончания договора</Data></Cell>
    <Cell ss:StyleID="s66"><Data ss:Type="String">Дата подписания сторонами</Data></Cell>
    <Cell ss:StyleID="s66"><Data ss:Type="String">Альтернативный получатель платежа</Data></Cell>
    <Cell ss:StyleID="s66"><Data ss:Type="String">ИНН Альтернативного получателя платежа</Data></Cell>
    <Cell ss:StyleID="s66"><Data ss:Type="String">КПП Альтернативного получателя платежа</Data></Cell>
    <Cell ss:StyleID="s66"><Data ss:Type="String">Наименование  Альтернативного получателя платежа</Data></Cell>
    <Cell ss:StyleID="s66"><Data ss:Type="String">Ссылка на карточку документа</Data></Cell>
    <Cell ss:StyleID="s66"><Data ss:Type="String">КБК</Data></Cell>
    <Cell ss:StyleID="s66"><Data ss:Type="String">Отчетная дата</Data></Cell>
    <Cell ss:StyleID="s67"/>
   </Row>
   <Row ss:AutoFitHeight="0" ss:Height="15.75">
    <Cell ss:StyleID="s65"><Data ss:Type="Number">1</Data></Cell>
    <Cell ss:StyleID="s65"><Data ss:Type="Number">2</Data></Cell>
    <Cell ss:StyleID="s65"><Data ss:Type="Number">3</Data></Cell>
    <Cell ss:StyleID="s65"><Data ss:Type="Number">4</Data></Cell>
    <Cell ss:StyleID="s65"><Data ss:Type="Number">5</Data></Cell>
    <Cell ss:StyleID="s65"><Data ss:Type="Number">6</Data></Cell>
    <Cell ss:StyleID="s65"><Data ss:Type="Number">7</Data></Cell>
    <Cell ss:StyleID="s65"><Data ss:Type="Number">8</Data></Cell>
    <Cell ss:StyleID="s65"><Data ss:Type="Number">9</Data></Cell>
    <Cell ss:StyleID="s65"><Data ss:Type="Number">10</Data></Cell>
    <Cell ss:StyleID="s65"><Data ss:Type="Number">11</Data></Cell>
    <Cell ss:StyleID="s65"><Data ss:Type="Number">12</Data></Cell>
    <Cell ss:StyleID="s65"><Data ss:Type="Number">13</Data></Cell>
    <Cell ss:StyleID="s65"><Data ss:Type="Number">14</Data></Cell>
    <Cell ss:StyleID="s65"><Data ss:Type="Number">15</Data></Cell>
    <Cell ss:StyleID="s65"><Data ss:Type="Number">16</Data></Cell>
    <Cell ss:StyleID="s65"><Data ss:Type="Number">17</Data></Cell>
    <Cell ss:StyleID="s65"><Data ss:Type="Number">18</Data></Cell>
    <Cell ss:StyleID="s65"><Data ss:Type="Number">19</Data></Cell>
    <Cell ss:StyleID="s65"><Data ss:Type="Number">20</Data></Cell>
    <Cell ss:StyleID="s65"><Data ss:Type="Number">21</Data></Cell>
    <Cell ss:StyleID="s65"><Data ss:Type="Number">22</Data></Cell>
    <Cell ss:StyleID="s65"><Data ss:Type="Number">23</Data></Cell>
    <Cell ss:StyleID="s65"><Data ss:Type="Number">24</Data></Cell>
    <Cell ss:StyleID="s65"><Data ss:Type="Number">25</Data></Cell>
    <Cell ss:StyleID="s65"><Data ss:Type="Number">26</Data></Cell>
    <Cell ss:StyleID="s65"><Data ss:Type="Number">27</Data></Cell>
    <Cell ss:StyleID="s65"><Data ss:Type="Number">28</Data></Cell>
    <Cell ss:StyleID="s65"><Data ss:Type="Number">29</Data></Cell>
    <Cell ss:StyleID="s65"><Data ss:Type="Number">30</Data></Cell>
    <Cell ss:StyleID="s65"><Data ss:Type="Number">31</Data></Cell>
    <Cell ss:StyleID="s65"><Data ss:Type="Number">32</Data></Cell>
    <Cell ss:StyleID="s65"><Data ss:Type="Number">33</Data></Cell>
    <Cell ss:StyleID="s65"><Data ss:Type="Number">34</Data></Cell>
    <Cell ss:StyleID="s65"><Data ss:Type="Number">35</Data></Cell>
    <Cell ss:StyleID="s65"><Data ss:Type="Number">36</Data></Cell>
    <Cell ss:StyleID="s65"><Data ss:Type="Number">37</Data></Cell>
    <Cell ss:StyleID="s65"><Data ss:Type="Number">38</Data></Cell>
    <Cell ss:StyleID="s65"><Data ss:Type="Number">39</Data></Cell>
    <Cell ss:StyleID="s65"><Data ss:Type="Number">40</Data></Cell>
    <Cell ss:StyleID="s65"><Data ss:Type="Number">41</Data></Cell>
    <Cell ss:StyleID="s65"><Data ss:Type="Number">42</Data></Cell>
    <Cell ss:StyleID="s65"><Data ss:Type="Number">43</Data></Cell>
    <Cell ss:StyleID="s65"><Data ss:Type="Number">44</Data></Cell>
    <Cell ss:StyleID="s65"><Data ss:Type="Number">45</Data></Cell>
    <Cell ss:StyleID="s65"><Data ss:Type="Number">46</Data></Cell>
    <Cell ss:StyleID="s65"><Data ss:Type="Number">47</Data></Cell>
    <Cell ss:StyleID="s65"><Data ss:Type="Number">48</Data></Cell>
    <Cell ss:StyleID="s65"><Data ss:Type="Number">49</Data></Cell>
    <Cell ss:StyleID="s65"><Data ss:Type="Number">50</Data></Cell>
    <Cell ss:StyleID="s65"><Data ss:Type="Number">51</Data></Cell>
    <Cell ss:StyleID="s65"><Data ss:Type="Number">52</Data></Cell>
    <Cell ss:StyleID="s65"><Data ss:Type="Number">53</Data></Cell>
    <Cell ss:StyleID="s65"><Data ss:Type="Number">54</Data></Cell>
    <Cell ss:StyleID="s65"><Data ss:Type="Number">55</Data></Cell>
    <Cell ss:StyleID="s65"><Data ss:Type="Number">56</Data></Cell>
    <Cell ss:StyleID="s65"><Data ss:Type="Number">57</Data></Cell>
    <Cell ss:StyleID="s65"><Data ss:Type="Number">58</Data></Cell>
    <Cell ss:StyleID="s68"><Data ss:Type="Number">59</Data></Cell>
    <Cell ss:StyleID="s68"><Data ss:Type="Number">60</Data></Cell>
    <Cell ss:StyleID="s68"><Data ss:Type="Number">61</Data></Cell>
    <Cell ss:StyleID="s68"><Data ss:Type="Number">62</Data></Cell>
    <Cell ss:StyleID="s68"><Data ss:Type="Number">63</Data></Cell>
    <Cell ss:StyleID="s68"><Data ss:Type="Number">64</Data></Cell>
    <Cell ss:StyleID="s68"><Data ss:Type="Number">65</Data></Cell>
    <Cell ss:StyleID="s68"><Data ss:Type="Number">66</Data></Cell>
    <Cell ss:StyleID="s68"><Data ss:Type="Number">67</Data></Cell>
    <Cell ss:StyleID="s69"><Data ss:Type="Number">68</Data></Cell>
    <Cell ss:StyleID="s68"><Data ss:Type="Number">69</Data></Cell>
    <Cell ss:StyleID="s68"><Data ss:Type="Number">70</Data></Cell>
    <Cell ss:StyleID="s70"/>
    <Cell ss:StyleID="s71"/>
   </Row>
   <Row ss:AutoFitHeight="0">
    <Cell ss:StyleID="s72"><Data ss:Type="String">[:a.kod_org]</Data></Cell>
    <Cell ss:StyleID="s72"><Data ss:Type="String">[:a.num_dog]</Data></Cell>
    <Cell ss:StyleID="s73"><Data ss:Type="String">[:a.id_dog]</Data></Cell>
    <Cell ss:StyleID="s74"><Data ss:Type="String">[:a.dat_dog]</Data></Cell>
    <Cell ss:StyleID="s72"><Data ss:Type="String">[:a.type_corr]</Data></Cell>
    <Cell ss:StyleID="s72"><Data ss:Type="String">[:a.id_ds]</Data></Cell>
    <Cell ss:StyleID="s72"><Data ss:Type="String">[:a.num_ds]</Data></Cell>
    <Cell ss:StyleID="s74"><Data ss:Type="String">[:a.dat_ds]</Data></Cell>
    <Cell ss:StyleID="s72"><Data ss:Type="String">[:a.id_org]</Data></Cell>
    <Cell ss:StyleID="s75"><Data ss:Type="String">[:a.inn]</Data></Cell>
    <Cell ss:StyleID="s75"><Data ss:Type="String">[:a.kpp]</Data></Cell>
    <Cell ss:StyleID="s72"><Data ss:Type="String">[:a.grp]</Data></Cell>
    <Cell ss:StyleID="s75"><Data ss:Type="String">[:a.name_org]</Data></Cell>
    <Cell ss:StyleID="s76"><Data ss:Type="String">[:a.poluch_pl]</Data></Cell>
    <Cell ss:StyleID="s75"/>
    <Cell ss:StyleID="s77"/>
    <Cell ss:StyleID="s78"/>
    <Cell ss:StyleID="s78"/>
    <Cell ss:StyleID="s78"/>
    <Cell ss:StyleID="s79"/>
    <Cell ss:StyleID="s79"/>
    <Cell ss:StyleID="s78"/>
    <Cell ss:StyleID="s80"/>
    <Cell ss:StyleID="s81"/>
    <Cell ss:StyleID="s72"><Data ss:Type="String">[:a.vid_dog]</Data></Cell>
    <Cell ss:StyleID="s72"><Data ss:Type="String">[:a.tip_dog]</Data></Cell>
    <Cell ss:StyleID="s72"><Data ss:Type="String">[:a.ini_dog]</Data></Cell>
    <Cell ss:StyleID="s72"><Data ss:Type="String">[:a.predm_dog]</Data></Cell>
    <Cell ss:StyleID="s72"/>
    <Cell ss:StyleID="s72"/>
    <Cell ss:StyleID="s72"><Data ss:Type="String">[:a.kod_val]</Data></Cell>
    <Cell ss:StyleID="s72"/>
    <Cell ss:StyleID="s72"><Data ss:Type="String">[:a.sum_vsego]</Data></Cell>
    <Cell ss:StyleID="s72"><Data ss:Type="String">[:a.proc]</Data></Cell>
    <Cell ss:StyleID="s72"><Data ss:Type="String">[:a.sum_bez_nds]</Data></Cell>
    <Cell ss:StyleID="s72"><Data ss:Type="String">[:a.sum_nds]</Data></Cell>
    <Cell ss:StyleID="s81"><Data ss:Type="String">[:a.pfm]</Data></Cell>
    <Cell ss:StyleID="s81"><Data ss:Type="String">[:a.finpos]</Data></Cell>
    <Cell ss:StyleID="s72"/>
    <Cell ss:StyleID="s72"/>
    <Cell ss:StyleID="s72"/>
    <Cell ss:StyleID="s72"/>
    <Cell ss:StyleID="s72"/>
    <Cell ss:StyleID="s72"/>
    <Cell ss:StyleID="s72"/>
    <Cell ss:StyleID="s72"/>
    <Cell ss:StyleID="s72"/>
    <Cell ss:StyleID="s72"/>
    <Cell ss:StyleID="s72"/>
    <Cell ss:StyleID="s72"/>
    <Cell ss:StyleID="s72"/>
    <Cell ss:StyleID="s72"/>
    <Cell ss:StyleID="s72"/>
    <Cell ss:StyleID="s72"/>
    <Cell ss:StyleID="s72"/>
    <Cell ss:StyleID="s72"/>
    <Cell ss:StyleID="s72"/>
    <Cell ss:StyleID="s72"/>
    <Cell ss:StyleID="s72"><Data ss:Type="String">[:a.status]</Data></Cell>
    <Cell ss:StyleID="s72"><Data ss:Type="String">[:a.kod_val_pl]</Data></Cell>
    <Cell ss:StyleID="s82"><Data ss:Type="String">[:a.dat_b_dog]</Data></Cell>
    <Cell ss:StyleID="s82"><Data ss:Type="String">[:a.dat_e_dog]</Data></Cell>
    <Cell ss:StyleID="s82"><Data ss:Type="String">[:a.dat_podpis]</Data></Cell>
    <Cell ss:StyleID="s72"/>
    <Cell ss:StyleID="s72"/>
    <Cell ss:StyleID="s72"/>
    <Cell ss:StyleID="s72"/>
    <Cell ss:StyleID="s72"/>
    <Cell ss:StyleID="s72"/>
    <Cell ss:StyleID="s72"/>
    <Cell ss:StyleID="s83" ss:Formula="=RC[-38]+1"><Data ss:Type="Error">#VALUE!</Data></Cell>
    <Cell ss:StyleID="s82"><Data ss:Type="String">[:a.text_prizn]</Data></Cell>
    <Cell><Data ss:Type="String">begin:a end:a;</Data></Cell>
   </Row>
  </Table>
  <WorksheetOptions xmlns="urn:schemas-microsoft-com:office:excel">
   <PageSetup>
    <Header x:Margin="0.3"/>
    <Footer x:Margin="0.3"/>
    <PageMargins x:Bottom="0.75" x:Left="0.7" x:Right="0.7" x:Top="0.75"/>
   </PageSetup>
   <Unsynced/>
   <Print>
    <ValidPrinterInfo/>
    <PaperSizeIndex>9</PaperSizeIndex>
    <HorizontalResolution>600</HorizontalResolution>
    <VerticalResolution>600</VerticalResolution>
   </Print>
   <Zoom>85</Zoom>
   <Selected/>
   <Panes>
    <Pane>
     <Number>3</Number>
     <ActiveRow>2</ActiveRow>
    </Pane>
   </Panes>
   <ProtectObjects>False</ProtectObjects>
   <ProtectScenarios>False</ProtectScenarios>
  </WorksheetOptions>
 </Worksheet>
</Workbook>
