<?xml version="1.0" encoding="utf-8"?>
<root>
  <form name="44212" timestamp="23.12.2019 19:47:28" file="sql.builder.templates\sql.builder\projects\44212\query\query.xml">
    <field id="31960895" controlType="UICombo" title="Договор" name="p_kod_dog" type="number" rows-limit="100" column-mandatory="1">
      <listquery>
        <query name="kr_dogovor_list_fin(dep)" />
      </listquery>
    </field>
    <fieldgroup title="Период" id="46143955">
      <field id="28954164" name="p_ym1" controlType="UICombo" type="number" title="C" column-mandatory="1">
        <listquery>
          <query name="spr_time_ym" />
        </listquery>
        <defaultquery>
          <query name="spr_time_ym_beg_year" />
        </defaultquery>
      </field>
      <field id="27868966" name="p_ym2" controlType="UICombo" type="number" title="По" column-mandatory="1">
        <listquery>
          <query name="spr_time_ym" />
        </listquery>
        <defaultquery>
          <query name="44212-ym2-val" />
        </defaultquery>
      </field>
    </fieldgroup>
    <field id="63212067" controlType="UIDate" type="date" title="На дату" name="p_dat" column-mandatory="1">
      <defaultquery>
        <query name="44212-dat-val" />
      </defaultquery>
    </field>
  </form>
  <dataset>
    <fields>
      <field type="number" name="p_kod_dog" parname="p_kod_dog" title="Договор" ColumnMandatory="1" />
      <field type="number" name="p_ym1" parname="p_ym1" title="C" ColumnMandatory="1" />
      <field type="number" name="p_ym2" parname="p_ym2" title="По" ColumnMandatory="1" />
      <field type="date" name="p_dat" parname="p_dat" title="На дату" ColumnMandatory="1" />
      <field type="string" name="is_form_valid" parname="is_form_valid" />
      <field type="string" name="is_form_valid_not" parname="is_form_valid_not" />
    </fields>
  </dataset>
</root>