<?xml version="1.0" encoding="utf-8"?>
<root>
  <form name="52733" timestamp="30.01.2023 11:53:13" file="sql.builder.templates\sql.builder\projects\49277\reports\52733-rep.xml" elid="92" ord="92" leaf="0" lvl="2" pelid="">
    <field id="39725486" controlType="UICombo" type="number" name="year" title="Год" column-mandatory="1">
      <listquery>
        <query name="52733_year" />
      </listquery>
      <defaultquery>
        <query name="52733_year_def" />
      </defaultquery>
    </field>
    <field id="45907341" controlType="UIList" title="Филиал" name="kod_fl" type="number" column-mandatory="1">
      <listquery>
        <query name="jv_rep_cons_d_fl" />
      </listquery>
      <defaultquery>
        <query name="45862-kod_fl-def" />
      </defaultquery>
    </field>
    <field id="59221536" controlType="UIList" title="Подстанции" name="hv_eopwrc_id" type="string" column-mandatory="1">
      <listquery>
        <query name="52733_pwrc_list" />
      </listquery>
      <defaultquery>
        <query name="52733_pwrc_def" />
      </defaultquery>
    </field>
    <field id="36225385" controlType="UIList" title="Подстанции" name="pwrc_id" type="number" column-mandatory="1" visible="0">
      <defaultquery>
        <query name="vr_rb_pwrc_list_by_hv_eopwrc_id" />
      </defaultquery>
    </field>
    <field id="2833856" controlType="UIList" title="Фидеры" name="k_kg_name" type="string" column-mandatory="1" column-visible="0">
      <defaultquery>
        <query name="52733_k_kg_name" />
      </defaultquery>
    </field>
    <field id="50886679" controlType="UIList" title="Фидеры" name="pwrc_fdrid" type="number" column-mandatory="1">
      <listquery>
        <query name="45862_fdr_by_kn_name_list_test2" />
      </listquery>
      <defaultquery>
        <query name="45862_fdr_by_kn_name_list_test2" />
      </defaultquery>
    </field>
    <field id="32620598" controlType="UITextEx" type="string" name="kg_missing_tp_text" column-editable="0" title="ТП, которые необходимо включить в КГ">
      <defaultquery>
        <query name="52733_fdr_kg_missing_tp_single_year_text" />
      </defaultquery>
    </field>
  </form>
  <dataset>
    <fields>
      <field type="number" name="year" parname="year" title="Год" ColumnMandatory="1" />
      <field type="number" name="kod_fl" parname="kod_fl" title="Филиал" ColumnMandatory="1" />
      <field type="string" name="hv_eopwrc_id" parname="hv_eopwrc_id" title="Подстанции" ColumnMandatory="1" />
      <field type="number" name="pwrc_id" parname="pwrc_id" title="Подстанции" ColumnMandatory="1" ClientVisible="0" />
      <field type="string" name="k_kg_name" parname="k_kg_name" title="Фидеры" ColumnMandatory="1" ColumnVisible="0" />
      <field type="number" name="pwrc_fdrid" parname="pwrc_fdrid" title="Фидеры" ColumnMandatory="1" />
      <field type="string" name="kg_missing_tp_text" parname="kg_missing_tp_text" title="ТП, которые необходимо включить в КГ" ColumnEditable="0" />
      <field type="string" name="is_form_valid" parname="is_form_valid" />
      <field type="string" name="is_form_valid_not" parname="is_form_valid_not" />
    </fields>
  </dataset>
</root>