<root>
  <queries>
    <query name="kr_object">
      <select>
        <column table="a" column="kod_obj" type="number">
        </column>
        <column table="a" column="kodd" type="number">
        </column>
        <call function="nk_adress.kf_address" as="adr">
          <const>1</const>
          <column table="a" column="kodd">
          </column>
        </call>
        <column table="adr" column="adr_m_name" as="adr_m_name">
        </column>
        <column table="adr" column="kod_m">
        </column>
      </select>
      <from>
        <table name="kr_object" as="a">
        </table>
        <query name="k_house" as="adr" join="left outer">
          <call function="=">
            <column table="a" column="kodd">
            </column>
            <column table="adr" column="kodd">
            </column>
          </call>
        </query>
      </from>
    </query>
  </queries>
</root>