<?xml version="1.0" encoding="utf-8"?>
<root timestamp="17.10.2024 11:10:25">
  <scheme>
    <table name="main72489" as="a">
      <columns>
        <column name="sequential_number" type="number" into="sequential_number" key="0" />
        <column name="full_name_subscriber" type="string" into="full_name_subscriber" key="0" />
        <column name="short_name_subscriber" type="string" into="short_name_subscriber" key="0" />
        <column name="inn_subscriber" type="string" into="inn_subscriber" key="0" />
        <column name="contract_number_date" type="string" into="contract_number_date" key="0" />
        <column name="legal_address" type="string" into="legal_address" key="0" />
        <column name="postal_address" type="string" into="postal_address" key="0" />
        <column name="name_object" type="string" into="name_object" key="0" />
        <column name="address_object" type="string" into="address_object" key="0" />
        <column name="number_object" type="number" into="number_object" key="0" />
        <column name="description_connection" type="string" into="description_connection" key="0" />
        <column name="supply_point" type="string" into="supply_point" key="0" />
        <column name="maximum_power" type="number" into="maximum_power" key="0" />
        <column name="connected_power" type="number" into="connected_power" key="0" />
        <column name="tangent_phi" type="number" into="tangent_phi" key="0" />
        <column name="number_metering_point" type="number" into="number_metering_point" key="0" />
        <column name="type_metering_point" type="string" into="type_metering_point" key="0" />
        <column name="place_installation" type="string" into="place_installation" key="0" />
        <column name="type_el_meter" type="string" into="type_el_meter" key="0" />
        <column name="number_el_meter" type="string" into="number_el_meter" key="0" />
        <column name="enrg_name" type="string" into="enrg_name" key="0" />
        <column name="i1" type="string" into="i1" key="0" />
        <column name="i2" type="string" into="i2" key="0" />
        <column name="u1" type="string" into="u1" key="0" />
        <column name="u2" type="string" into="u2" key="0" />
        <column name="design_factor" type="string" into="design_factor" key="0" />
        <column name="prev_verif_el_meter" type="string" into="prev_verif_el_meter" key="0" />
        <column name="next_verif_el_meter" type="string" into="next_verif_el_meter" key="0" />
        <column name="service_line_el_meter" type="number" into="service_line_el_meter" key="0" />
        <column name="characteristic_location" type="string" into="characteristic_location" key="0" />
        <column name="variable_loss" type="string" into="variable_loss" key="0" />
        <column name="balance_affilation" type="string" into="balance_affilation" key="0" />
        <column name="voltage_level_tariff" type="string" into="voltage_level_tariff" key="0" />
        <column name="tariff_option" type="string" into="tariff_option" key="0" />
        <column name="price_category" type="number" into="price_category" key="0" />
        <column name="name_group_supply_points" type="string" into="name_group_supply_points" key="0" />
        <column name="atp" type="string" into="atp" key="0" />
        <column name="asb" type="string" into="asb" key="0" />
        <column name="amount_emergency_reservation" type="string" into="amount_emergency_reservation" key="0" />
        <column name="reliability_category" type="string" into="reliability_category" key="0" />
      </columns>
      <viewcolumns>
        <column table="a" name="sequential_number" type="number" into="sequential_number" assigned="1" visible="0" />
        <column table="a" name="full_name_subscriber" type="string" into="full_name_subscriber" assigned="1" visible="0" />
        <column table="a" name="short_name_subscriber" type="string" into="short_name_subscriber" assigned="1" visible="0" />
        <column table="a" name="inn_subscriber" type="string" into="inn_subscriber" assigned="1" visible="0" />
        <column table="a" name="contract_number_date" type="string" into="contract_number_date" assigned="1" visible="0" />
        <column table="a" name="legal_address" type="string" into="legal_address" assigned="1" visible="0" />
        <column table="a" name="postal_address" type="string" into="postal_address" assigned="1" visible="0" />
        <column table="a" name="name_object" type="string" into="name_object" assigned="1" visible="0" />
        <column table="a" name="address_object" type="string" into="address_object" assigned="1" visible="0" />
        <column table="a" name="number_object" type="number" into="number_object" assigned="1" visible="0" />
        <column table="a" name="description_connection" type="string" into="description_connection" assigned="1" visible="0" />
        <column table="a" name="supply_point" type="string" into="supply_point" assigned="1" visible="0" />
        <column table="a" name="maximum_power" type="number" into="maximum_power" assigned="1" visible="0" />
        <column table="a" name="connected_power" type="number" into="connected_power" assigned="1" visible="0" />
        <column table="a" name="tangent_phi" type="number" into="tangent_phi" assigned="1" visible="0" />
        <column table="a" name="number_metering_point" type="number" into="number_metering_point" assigned="1" visible="0" />
        <column table="a" name="type_metering_point" type="string" into="type_metering_point" assigned="1" visible="0" />
        <column table="a" name="place_installation" type="string" into="place_installation" assigned="1" visible="0" />
        <column table="a" name="type_el_meter" type="string" into="type_el_meter" assigned="1" visible="0" />
        <column table="a" name="number_el_meter" type="string" into="number_el_meter" assigned="1" visible="0" />
        <column table="a" name="enrg_name" type="string" into="enrg_name" assigned="1" visible="0" />
        <column table="a" name="i1" type="string" into="i1" assigned="1" visible="0" />
        <column table="a" name="i2" type="string" into="i2" assigned="1" visible="0" />
        <column table="a" name="u1" type="string" into="u1" assigned="1" visible="0" />
        <column table="a" name="u2" type="string" into="u2" assigned="1" visible="0" />
        <column table="a" name="design_factor" type="string" into="design_factor" assigned="1" visible="0" />
        <column table="a" name="prev_verif_el_meter" type="string" into="prev_verif_el_meter" assigned="1" visible="0" />
        <column table="a" name="next_verif_el_meter" type="string" into="next_verif_el_meter" assigned="1" visible="0" />
        <column table="a" name="service_line_el_meter" type="number" into="service_line_el_meter" assigned="1" visible="0" />
        <column table="a" name="characteristic_location" type="string" into="characteristic_location" assigned="1" visible="0" />
        <column table="a" name="variable_loss" type="string" into="variable_loss" assigned="1" visible="0" />
        <column table="a" name="balance_affilation" type="string" into="balance_affilation" assigned="1" visible="0" />
        <column table="a" name="voltage_level_tariff" type="string" into="voltage_level_tariff" assigned="1" visible="0" />
        <column table="a" name="tariff_option" type="string" into="tariff_option" assigned="1" visible="0" />
        <column table="a" name="price_category" type="number" into="price_category" assigned="1" visible="0" />
        <column table="a" name="name_group_supply_points" type="string" into="name_group_supply_points" assigned="1" visible="0" />
        <column table="a" name="atp" type="string" into="atp" assigned="1" visible="0" />
        <column table="a" name="asb" type="string" into="asb" assigned="1" visible="0" />
        <column table="a" name="amount_emergency_reservation" type="string" into="amount_emergency_reservation" assigned="1" visible="0" />
        <column table="a" name="reliability_category" type="string" into="reliability_category" assigned="1" visible="0" />
      </viewcolumns>
    </table>
  </scheme>
</root>